README.md
setup.cfg
setup.py
travis_talk/__init__.py
travis_talk/command_line.py
travis_talk.egg-info/PKG-INFO
travis_talk.egg-info/SOURCES.txt
travis_talk.egg-info/dependency_links.txt
travis_talk.egg-info/entry_points.txt
travis_talk.egg-info/not-zip-safe
travis_talk.egg-info/top_level.txt
travis_talk/bin/dumb-md5-hash