Metadata-Version: 1.0
Name: travis-talk
Version: 0.7
Summary: a testament to the arrogance and folly of man
Home-page: UNKNOWN
Author: rusty shackleford
Author-email: UNKNOWN
License: none
Platform: UNKNOWN
